Metadata-Version: 2.1
Name: chrome-profile-extractor
Version: 1.0.0
Summary: this package for education purpose only.
Home-page:  https://github.com/HanZawNyein/chrome-profile-extractor.git
Author: Han Zaw Nyein
Author-email: hanzawnyineonline@gmail.com
License: UNKNOWN
Platform: UNKNOWN
